sceneprogrenderer/__init__.py
sceneprogrenderer/renderer.py
sceneprogrenderer/utils.py
sceneprogrenderer-0.1.2.dist-info/METADATA
sceneprogrenderer-0.1.2.dist-info/WHEEL
sceneprogrenderer-0.1.2.dist-info/top_level.txt
sceneprogrenderer-0.1.2.dist-info/RECORD
