Metadata-Version: 2.2
Name: sceneprogrenderer
Version: 0.1.2
Summary: A Renderer built for the SceneProg project
Home-page: https://github.com/KunalMGupta/sceneprogrenderer.git
Author: Kunal Gupta
Author-email: k5upta@ucsd.edu
Classifier: Programming Language :: Python :: 3
Classifier: License :: OSI Approved :: MIT License
Classifier: Operating System :: OS Independent
Requires-Python: >=3.9
Dynamic: author
Dynamic: author-email
Dynamic: classifier
Dynamic: description
Dynamic: description-content-type
Dynamic: home-page
Dynamic: requires-python
Dynamic: summary
